ynabapiimport/__init__.py
ynabapiimport/accountclient.py
ynabapiimport/accountfetcher.py
ynabapiimport/memocleaner.py
ynabapiimport/models/config.py
ynabapiimport/models/exceptions.py
ynabapiimport/models/transaction.py
ynabapiimport/requisitionhandler.py
ynabapiimport/ynabapiimport.py
ynabapiimport/ynabclient.py
ynab_api_import-2.0.0.dist-info/LICENSE
ynab_api_import-2.0.0.dist-info/METADATA
ynab_api_import-2.0.0.dist-info/WHEEL
ynab_api_import-2.0.0.dist-info/RECORD
