Metadata-Version: 2.1
Name: ynab-api-import
Version: 2.0.0
Summary: Library to import bank transactions via API into You Need A Budget (YNAB)
License: MIT
Author: Daniel Basta
Author-email: ynab@basta.info
Requires-Python: >=3.8,<4.0
Classifier: License :: OSI Approved :: MIT License
Classifier: Operating System :: OS Independent
Classifier: Programming Language :: Python :: 3
Classifier: Programming Language :: Python :: 3.8
Classifier: Programming Language :: Python :: 3.9
Classifier: Programming Language :: Python :: 3.10
Classifier: Programming Language :: Python :: 3.11
Classifier: Programming Language :: Python :: 3.12
Classifier: Programming Language :: Python :: 3.13
Requires-Dist: nordigen (>=1.4)
Requires-Dist: pytest (>=8.3.3,<9.0.0)
Requires-Dist: pyyaml (>=6.0)
Requires-Dist: requests (>=2.28)
